[{"name":"ertert","lastname":"ertert","dob":"2017-11-22","address":"dfgdf","city":"dfgsdfg","zip":"3456","state":"fg","phone":"3645656","em_firstname":"gfhdgh","em_lastname":"dfhgfh","em_phone":"564567457","skill":"Level 2","status":"Active","note":"","photoPath":"boy4.jpg","fullName":"ertert ertert","fullAddress":"dfgdf dfgsdfg fg 3456","gender":"MALE","checkedStatus":"Checked out","registrationDate":{"year":2018,"month":11,"day":2},"id":"a0fa828","visits":[]},{"name":"jhkghjk","lastname":"khjfkk","dob":"2016-11-10","address":"ghj","city":"fgjgh","zip":"457645","state":"56","phone":"457","em_firstname":"gfj","em_lastname":"jfghj","em_phone":"567856","skill":"Level 2","status":"Active","note":"","photoPath":"girl4.jpg","fullName":"jhkghjk khjfkk","fullAddress":"ghj fgjgh 56 457645","gender":"FEMALE","checkedStatus":"Checked out","registrationDate":{"year":2018,"month":11,"day":2},"id":"5d13dfee","visits":[]}]
